README.md
setup.py
linalg/__init__.py
linalg/vector.py
linalg_simple.egg-info/PKG-INFO
linalg_simple.egg-info/SOURCES.txt
linalg_simple.egg-info/dependency_links.txt
linalg_simple.egg-info/not-zip-safe
linalg_simple.egg-info/top_level.txt