Metadata-Version: 2.1
Name: linalg-simple
Version: 0.0.3
Summary: Simple Linear Algebra Package
Home-page: https://github.com/thomasgrusz/linalg_pkg
Author: Thomas Grusz
Author-email: thomas.grusz@gmail.com
License: UNKNOWN
Platform: UNKNOWN
Requires-Python: >=3.6
